pubsub_az/__init__.py
pubsub_az/client/__init__.py
pubsub_az/client/client.py
pubsub_az/env/__init__.py
pubsub_az/env/env.py
pubsub_az/util/__init__.py
pubsub_az/util/util.py
pubsub_az-0.1.2.dist-info/METADATA
pubsub_az-0.1.2.dist-info/WHEEL
pubsub_az-0.1.2.dist-info/entry_points.txt
pubsub_az-0.1.2.dist-info/top_level.txt
pubsub_az-0.1.2.dist-info/RECORD
