Metadata-Version: 2.1
Name: pubsub-az
Version: 0.1.2
Summary: Python SDK for Azure Web PubSub
Author-email: Marcel Claramunt <marcel@moveread.com>
Project-URL: home, https://github.com/moveread/azure-sdks/tree/main/sdks/pubsub-az
Project-URL: repo, https://github.com/moveread/azure-sdks
Requires-Python: >=3.10
Requires-Dist: azure-messaging-webpubsubservice
Requires-Dist: aiohttp
Provides-Extra: client
Requires-Dist: azure-messaging-webpubsubclient ; extra == 'client'
Requires-Dist: python-dotenv ; extra == 'client'
